smassh/__init__.py
smassh/__main__.py
smassh/src/__init__.py
smassh/src/buddy.py
smassh/src/converter.py
smassh/src/css_generator.py
smassh/src/figlet.py
smassh/src/generator.py
smassh/src/help_menu.py
smassh/src/stats_tracker.py
smassh/src/tracker.py
smassh/src/parser/__init__.py
smassh/src/parser/config_parser.py
smassh/src/parser/data_parser.py
smassh/src/parser/parser.py
smassh/src/plugins/__init__.py
smassh/src/plugins/add_language.py
smassh/ui/__init__.py
smassh/ui/css.py
smassh/ui/events.py
smassh/ui/tui.py
smassh/ui/css/base.tcss
smassh/ui/css/themes/8008.tcss
smassh/ui/css/themes/80s_after_dark.tcss
smassh/ui/css/themes/9009.tcss
smassh/ui/css/themes/aether.tcss
smassh/ui/css/themes/alduin.tcss
smassh/ui/css/themes/alpine.tcss
smassh/ui/css/themes/arch.tcss
smassh/ui/css/themes/aurora.tcss
smassh/ui/css/themes/beach.tcss
smassh/ui/css/themes/bento.tcss
smassh/ui/css/themes/bingsu.tcss
smassh/ui/css/themes/bliss.tcss
smassh/ui/css/themes/blue_dolphin.tcss
smassh/ui/css/themes/blueberry_dark.tcss
smassh/ui/css/themes/blueberry_light.tcss
smassh/ui/css/themes/botanical.tcss
smassh/ui/css/themes/bouquet.tcss
smassh/ui/css/themes/breeze.tcss
smassh/ui/css/themes/bushido.tcss
smassh/ui/css/themes/cafe.tcss
smassh/ui/css/themes/camping.tcss
smassh/ui/css/themes/carbon.tcss
smassh/ui/css/themes/catppuccin.tcss
smassh/ui/css/themes/chaos_theory.tcss
smassh/ui/css/themes/cheesecake.tcss
smassh/ui/css/themes/cherry_blossom.tcss
smassh/ui/css/themes/comfy.tcss
smassh/ui/css/themes/copper.tcss
smassh/ui/css/themes/creamsicle.tcss
smassh/ui/css/themes/cyberspace.tcss
smassh/ui/css/themes/dark.tcss
smassh/ui/css/themes/dark_magic_girl.tcss
smassh/ui/css/themes/dark_note.tcss
smassh/ui/css/themes/darling.tcss
smassh/ui/css/themes/deku.tcss
smassh/ui/css/themes/desert_oasis.tcss
smassh/ui/css/themes/dev.tcss
smassh/ui/css/themes/diner.tcss
smassh/ui/css/themes/dino.tcss
smassh/ui/css/themes/dmg.tcss
smassh/ui/css/themes/dollar.tcss
smassh/ui/css/themes/dots.tcss
smassh-3.2.1.dist-info/METADATA
smassh-3.2.1.dist-info/WHEEL
smassh-3.2.1.dist-info/entry_points.txt
smassh-3.2.1.dist-info/licenses/LICENSE
smassh-3.2.1.dist-info/RECORD
