Metadata-Version: 2.4
Name: smassh
Version: 3.2.1
Summary: A TUI based typing application
Project-URL: Homepage, https://github.com/kraanzu/smassh
Project-URL: Repository, https://github.com/kraanzu/smassh
Author-email: kraanzu <kraanzu@gmail.com>
Maintainer-email: kraanzu <kraanzu@gmail.com>
License: GPL v3
License-File: LICENSE
Requires-Python: >=3.9
Requires-Dist: click>=8.1.7
Requires-Dist: platformdirs>=4.3.6
Requires-Dist: requests>=2.31.0
Requires-Dist: textual>=3.2.0
